[{"name_with_stand":"Aaron JudgeR","attack_angle":14.7220595987,"attack_direction":-4.3987973598,"swing_path_tilt":39.7505670423,"bat_speed":76.443},{"name_with_stand":"Adley RutschmanL","attack_angle":13.3140751623,"attack_direction":4.0060888369,"swing_path_tilt":34.8497671432,"bat_speed":70.1397163121},{"name_with_stand":"Adley RutschmanR","attack_angle":8.7878268066,"attack_direction":-6.3687073289,"swing_path_tilt":34.769814752,"bat_speed":69.0511111111},{"name_with_stand":"Adolis GarciaR","attack_angle":10.2797522278,"attack_direction":-2.8962307844,"swing_path_tilt":29.5932035834,"bat_speed":70.9503957784},{"name_with_stand":"Alec BohmR","attack_angle":7.6733588002,"attack_direction":1.022770257,"swing_path_tilt":30.5525400503,"bat_speed":72.0561643836},{"name_with_stand":"Alec BurlesonL","attack_angle":10.2790980708,"attack_direction":-1.8759944467,"swing_path_tilt":33.5035480089,"bat_speed":70.4692098093},{"name_with_stand":"Alex BregmanR","attack_angle":12.04339583,"attack_direction":-1.8955710209,"swing_path_tilt":27.7693318051,"bat_speed":70.918705036},{"name_with_stand":"Alex VerdugoL","attack_angle":5.1230184715,"attack_direction":1.5376028802,"swing_path_tilt":31.8744385499,"bat_speed":68.7122222222},{"name_with_stand":"Andres GimenezL","attack_angle":7.5252348414,"attack_direction":-0.1867654381,"swing_path_tilt":32.9119214761,"bat_speed":66.3800569801},{"name_with_stand":"Andrew BenintendiL","attack_angle":12.2568981368,"attack_direction":-0.1367299219,"swing_path_tilt":35.0478077342,"bat_speed":65.7022556391},{"name_with_stand":"Andrew McCutchenR","attack_angle":11.5103395174,"attack_direction":2.938776222,"swing_path_tilt":33.8098144315,"bat_speed":72.56},{"name_with_stand":"Andrew VaughnR","attack_angle":10.5865847842,"attack_direction":-4.9941112213,"swing_path_tilt":29.3227992216,"bat_speed":71.14},{"name_with_stand":"Anthony SantanderL","attack_angle":9.5050927395,"attack_direction":9.412734002,"swing_path_tilt":25.5192515321,"bat_speed":72.7861423221},{"name_with_stand":"Anthony SantanderR","attack_angle":6.4067034127,"attack_direction":-2.5273496138,"swing_path_tilt":28.0454803084,"bat_speed":74.404},{"name_with_stand":"Anthony VolpeR","attack_angle":6.4822075291,"attack_direction":10.264764495,"swing_path_tilt":33.4395578426,"bat_speed":65.8194244604},{"name_with_stand":"Bobby Witt Jr.R","attack_angle":7.6058557332,"attack_direction":-5.0539090149,"swing_path_tilt":29.5258101269,"bat_speed":75.2665803109},{"name_with_stand":"Brandon NimmoL","attack_angle":6.9836581287,"attack_direction":0.0348008644,"swing_path_tilt":28.3865773679,"bat_speed":72.2790190736},{"name_with_stand":"Brendan DonovanL","attack_angle":6.725567936,"attack_direction":1.1248979688,"swing_path_tilt":30.1235386203,"bat_speed":67.9513513514},{"name_with_stand":"Brendan RodgersR","attack_angle":3.8074735112,"attack_direction":-0.0881801237,"swing_path_tilt":31.9365266275,"bat_speed":69.1186619718},{"name_with_stand":"Brent RookerR","attack_angle":11.6205009425,"attack_direction":-5.8520894821,"swing_path_tilt":35.8192007364,"bat_speed":72.7479381443},{"name_with_stand":"Brenton DoyleR","attack_angle":11.8998621288,"attack_direction":0.0299888177,"swing_path_tilt":31.8766087859,"bat_speed":68.6073569482},{"name_with_stand":"Brice TurangL","attack_angle":-1.8343965592,"attack_direction":-4.5751200299,"swing_path_tilt":30.6548943865,"bat_speed":61.5630597015},{"name_with_stand":"Bryan De La CruzR","attack_angle":11.9582875605,"attack_direction":1.7798148787,"swing_path_tilt":38.5811426786,"bat_speed":71.397574124},{"name_with_stand":"Bryan ReynoldsL","attack_angle":13.0033535112,"attack_direction":-0.3662345166,"swing_path_tilt":38.6242732112,"bat_speed":69.8616666667},{"name_with_stand":"Bryan ReynoldsR","attack_angle":9.6328137404,"attack_direction":3.4758007602,"swing_path_tilt":37.7423429481,"bat_speed":72.4844262295},{"name_with_stand":"Bryce HarperL","attack_angle":11.3889026817,"attack_direction":0.3383701699,"swing_path_tilt":36.0721038353,"bat_speed":73.4068075117},{"name_with_stand":"Bryson StottL","attack_angle":7.926207587,"attack_direction":-0.7611873896,"swing_path_tilt":32.2724129679,"bat_speed":66.8146067416},{"name_with_stand":"CJ AbramsL","attack_angle":11.803725186,"attack_direction":2.1630692386,"swing_path_tilt":29.5225505333,"bat_speed":70.7753462604},{"name_with_stand":"Cal RaleighL","attack_angle":16.4919073976,"attack_direction":6.7515080565,"swing_path_tilt":33.2627329993,"bat_speed":73.4348920863},{"name_with_stand":"Cal RaleighR","attack_angle":18.5380242658,"attack_direction":-16.7691365677,"swing_path_tilt":31.0502079303,"bat_speed":74.3279661017},{"name_with_stand":"Carlos SantanaL","attack_angle":13.0475298637,"attack_direction":6.5915820057,"swing_path_tilt":27.5870883384,"bat_speed":71.6005102041},{"name_with_stand":"Carlos SantanaR","attack_angle":11.0941762788,"attack_direction":-6.6408237454,"swing_path_tilt":25.5549045395,"bat_speed":73.5016949153},{"name_with_stand":"Ceddanne RafaelaR","attack_angle":14.2386201971,"attack_direction":-0.9797238733,"swing_path_tilt":34.4551739809,"bat_speed":67.9054830287},{"name_with_stand":"Cedric MullinsL","attack_angle":8.0930580778,"attack_direction":11.4252270307,"swing_path_tilt":31.8041970453,"bat_speed":65.2860627178},{"name_with_stand":"Christian WalkerR","attack_angle":8.6372834503,"attack_direction":-2.3464182415,"swing_path_tilt":30.364431951,"bat_speed":73.2081784387},{"name_with_stand":"Christopher MorelR","attack_angle":12.0847592011,"attack_direction":-3.8438670947,"swing_path_tilt":27.754820816,"bat_speed":75.1122340426},{"name_with_stand":"Cody BellingerL","attack_angle":14.7921654314,"attack_direction":4.1584495087,"swing_path_tilt":32.8965844306,"bat_speed":69.4312714777},{"name_with_stand":"Colt KeithL","attack_angle":7.7461984289,"attack_direction":-1.1689301894,"swing_path_tilt":33.0065929915,"bat_speed":69.7126712329},{"name_with_stand":"Colton CowserL","attack_angle":14.4359777398,"attack_direction":-0.4072630648,"swing_path_tilt":39.8208128431,"bat_speed":72.6319391635},{"name_with_stand":"Corbin CarrollL","attack_angle":4.2847313353,"attack_direction":-1.8100157456,"swing_path_tilt":22.8982481263,"bat_speed":70.9981203008},{"name_with_stand":"Corey SeagerL","attack_angle":12.1755667249,"attack_direction":0.6211084283,"swing_path_tilt":33.9569237567,"bat_speed":71.6007936508},{"name_with_stand":"Dansby SwansonR","attack_angle":14.7903546216,"attack_direction":0.9347384037,"swing_path_tilt":35.294435205,"bat_speed":70.8395136778},{"name_with_stand":"Daulton VarshoL","attack_angle":10.4933299873,"attack_direction":3.4353902083,"swing_path_tilt":33.876564341,"bat_speed":70.57109375},{"name_with_stand":"Elly De La CruzL","attack_angle":10.536276443,"attack_direction":0.5223175485,"swing_path_tilt":35.8357511793,"bat_speed":75.0995689655},{"name_with_stand":"Elly De La CruzR","attack_angle":7.7898232311,"attack_direction":-8.5264952399,"swing_path_tilt":36.6018374549,"bat_speed":68.9765765766},{"name_with_stand":"Eugenio SuarezR","attack_angle":16.5953973149,"attack_direction":-1.4532233428,"swing_path_tilt":38.9932245586,"bat_speed":71.3754601227},{"name_with_stand":"Ezequiel TovarR","attack_angle":10.4497212348,"attack_direction":-3.2832446153,"swing_path_tilt":36.4698353917,"bat_speed":70.1238396624},{"name_with_stand":"Francisco LindorL","attack_angle":12.6405106946,"attack_direction":1.0783240143,"swing_path_tilt":35.2113112443,"bat_speed":71.6881226054},{"name_with_stand":"Francisco LindorR","attack_angle":12.7266926753,"attack_direction":-4.1425741997,"swing_path_tilt":31.4809816574,"bat_speed":72.4769230769},{"name_with_stand":"Freddie FreemanL","attack_angle":8.1681471095,"attack_direction":-1.0894375499,"swing_path_tilt":43.1519849797,"bat_speed":70.1220843672},{"name_with_stand":"Gavin LuxL","attack_angle":10.1221643516,"attack_direction":-3.7012809583,"swing_path_tilt":33.9487109175,"bat_speed":71.0407692308},{"name_with_stand":"George SpringerR","attack_angle":10.2329232204,"attack_direction":2.7176885938,"swing_path_tilt":33.6316524019,"bat_speed":70.8840236686},{"name_with_stand":"Giancarlo StantonR","attack_angle":7.6867033026,"attack_direction":-0.2694243133,"swing_path_tilt":26.7675403056,"bat_speed":80.9526970954},{"name_with_stand":"Gleyber TorresR","attack_angle":8.7354283937,"attack_direction":5.4939947963,"swing_path_tilt":34.880125982,"bat_speed":69.9948924731},{"name_with_stand":"Gunnar HendersonL","attack_angle":8.866923725,"attack_direction":-1.5770792952,"swing_path_tilt":30.5108394124,"bat_speed":75.9977272727},{"name_with_stand":"Heliot RamosR","attack_angle":6.73232775,"attack_direction":5.9452365797,"swing_path_tilt":33.5995269052,"bat_speed":73.813},{"name_with_stand":"Ian HappL","attack_angle":11.9018304683,"attack_direction":4.4378194779,"swing_path_tilt":34.2970444106,"bat_speed":72.1124},{"name_with_stand":"Ian HappR","attack_angle":4.2113690298,"attack_direction":-0.4917236251,"swing_path_tilt":30.7639554656,"bat_speed":69.5641304348},{"name_with_stand":"Isaac ParedesR","attack_angle":18.1042865302,"attack_direction":-22.0370351595,"swing_path_tilt":31.7449286967,"bat_speed":69.5788546256},{"name_with_stand":"J.D. MartinezR","attack_angle":12.8288869489,"attack_direction":-1.0651418051,"swing_path_tilt":38.9369429166,"bat_speed":71.6557894737},{"name_with_stand":"JJ BledayL","attack_angle":9.7880204212,"attack_direction":7.8676483607,"swing_path_tilt":29.6697198235,"bat_speed":69.1655279503},{"name_with_stand":"Jackson ChourioR","attack_angle":6.9699088876,"attack_direction":4.9564117925,"swing_path_tilt":26.9608210799,"bat_speed":71.9418867925},{"name_with_stand":"Jackson MerrillL","attack_angle":5.8647334456,"attack_direction":-0.2279136682,"swing_path_tilt":37.4841554997,"bat_speed":70.4967901235},{"name_with_stand":"Jacob YoungR","attack_angle":-5.3232209943,"attack_direction":-10.4710438478,"swing_path_tilt":37.4263326961,"bat_speed":54.612254902},{"name_with_stand":"Jake BurgerR","attack_angle":8.4954740218,"attack_direction":-6.8263944443,"swing_path_tilt":22.9443064349,"bat_speed":74.1412307692},{"name_with_stand":"Jake CronenworthL","attack_angle":4.8046752511,"attack_direction":-0.5327315532,"swing_path_tilt":33.6199090656,"bat_speed":67.1505617978},{"name_with_stand":"Jake MeyersR","attack_angle":6.9144218012,"attack_direction":-5.734815663,"swing_path_tilt":31.8455690322,"bat_speed":63.9089285714},{"name_with_stand":"Jarren DuranL","attack_angle":3.3427435276,"attack_direction":-2.2135582506,"swing_path_tilt":29.5035466034,"bat_speed":72.0646875},{"name_with_stand":"Jazz ChisholmL","attack_angle":14.6904755915,"attack_direction":6.7716422949,"swing_path_tilt":35.9385758176,"bat_speed":69.78125},{"name_with_stand":"Jeremy PenaR","attack_angle":7.840308266,"attack_direction":-5.9698695714,"swing_path_tilt":29.4130680781,"bat_speed":70.111369509},{"name_with_stand":"Jesse WinkerL","attack_angle":10.1243165073,"attack_direction":-9.0930889609,"swing_path_tilt":35.6557473234,"bat_speed":66.8660649819},{"name_with_stand":"Jesus SanchezL","attack_angle":8.5917430358,"attack_direction":-2.5020889425,"swing_path_tilt":30.9456395499,"bat_speed":74.4268072289},{"name_with_stand":"Joey OrtizR","attack_angle":1.8101638891,"attack_direction":-0.335534865,"swing_path_tilt":27.2828211506,"bat_speed":71.6107142857},{"name_with_stand":"Jonathan IndiaR","attack_angle":6.9925104083,"attack_direction":-0.6740775001,"swing_path_tilt":29.7731884699,"bat_speed":70.7523809524},{"name_with_stand":"Jorge SolerR","attack_angle":12.6799824314,"attack_direction":-11.7579219632,"swing_path_tilt":33.8155452428,"bat_speed":74.8375},{"name_with_stand":"Jose AltuveR","attack_angle":17.7062865545,"attack_direction":-6.0111400908,"swing_path_tilt":30.3862607618,"bat_speed":68.9061538462},{"name_with_stand":"Jose RamirezL","attack_angle":10.8532997152,"attack_direction":10.2815291638,"swing_path_tilt":32.5316749059,"bat_speed":70.1814345992},{"name_with_stand":"Jose RamirezR","attack_angle":5.636413434,"attack_direction":-2.4905013821,"swing_path_tilt":27.1806358546,"bat_speed":72.9975308642},{"name_with_stand":"Josh BellL","attack_angle":9.5204018436,"attack_direction":-1.0640941408,"swing_path_tilt":34.9042300537,"bat_speed":70.7503846154},{"name_with_stand":"Josh BellR","attack_angle":7.3425691127,"attack_direction":0.897491053,"swing_path_tilt":34.8131225995,"bat_speed":68.9144144144},{"name_with_stand":"Josh H. SmithL","attack_angle":13.0308322998,"attack_direction":8.0941719455,"swing_path_tilt":37.5681322049,"bat_speed":67.8037800687},{"name_with_stand":"Josh NaylorL","attack_angle":8.1919884402,"attack_direction":8.1611127799,"swing_path_tilt":29.5572611608,"bat_speed":71.7922330097},{"name_with_stand":"Juan SotoL","attack_angle":11.4875355413,"attack_direction":-4.7252298647,"swing_path_tilt":26.9118771333,"bat_speed":74.6529616725},{"name_with_stand":"Julio RodriguezR","attack_angle":7.5464349732,"attack_direction":-2.3123443587,"swing_path_tilt":33.3444779316,"bat_speed":74.821875},{"name_with_stand":"Jurickson ProfarL","attack_angle":9.6375403825,"attack_direction":5.9054129688,"swing_path_tilt":34.6216265425,"bat_speed":69.3355648536},{"name_with_stand":"Jurickson ProfarR","attack_angle":4.7895169271,"attack_direction":-6.3756129057,"swing_path_tilt":29.8760240774,"bat_speed":70.9641025641},{"name_with_stand":"Justin TurnerR","attack_angle":9.145235931,"attack_direction":0.3043158891,"swing_path_tilt":34.4441282513,"bat_speed":65.1880952381},{"name_with_stand":"Ketel MarteL","attack_angle":9.2145373491,"attack_direction":5.4565030739,"swing_path_tilt":33.836396737,"bat_speed":70.3224043716},{"name_with_stand":"Ketel MarteR","attack_angle":5.5221947714,"attack_direction":-2.4211323592,"swing_path_tilt":33.6192367386,"bat_speed":76.5558139535},{"name_with_stand":"Kyle SchwarberL","attack_angle":13.0432660175,"attack_direction":3.9072349263,"swing_path_tilt":29.4977446165,"bat_speed":75.2135135135},{"name_with_stand":"Lane ThomasR","attack_angle":8.9511001298,"attack_direction":-0.3053333394,"swing_path_tilt":29.8237866995,"bat_speed":70.8996309963},{"name_with_stand":"Leody TaverasL","attack_angle":6.4886009854,"attack_direction":5.8076280674,"swing_path_tilt":33.8269837559,"bat_speed":69.7432900433},{"name_with_stand":"Leody TaverasR","attack_angle":1.2047597907,"attack_direction":-13.3825905084,"swing_path_tilt":34.5964232722,"bat_speed":65.0517857143},{"name_with_stand":"Logan O'HoppeR","attack_angle":13.9576686605,"attack_direction":0.8174812255,"swing_path_tilt":33.5480811476,"bat_speed":69.1826855124},{"name_with_stand":"Lourdes GurrielR","attack_angle":9.5887542158,"attack_direction":-5.262435399,"swing_path_tilt":35.8345846124,"bat_speed":69.7543396226},{"name_with_stand":"Luis ArraezL","attack_angle":7.8499447361,"attack_direction":-1.2952514743,"swing_path_tilt":38.7127202643,"bat_speed":62.0352697095},{"name_with_stand":"Luis GarciaL","attack_angle":9.5166499565,"attack_direction":-0.135493133,"swing_path_tilt":29.548441479,"bat_speed":70.8825174825},{"name_with_stand":"Maikel GarciaR","attack_angle":3.2115340124,"attack_direction":3.2777381614,"swing_path_tilt":28.975041596,"bat_speed":68.2505119454},{"name_with_stand":"Manny MachadoR","attack_angle":6.25831229,"attack_direction":0.8537094078,"swing_path_tilt":26.3928868138,"bat_speed":74.077486911},{"name_with_stand":"Marcell OzunaR","attack_angle":15.2738460231,"attack_direction":-1.8917270076,"swing_path_tilt":36.4151461952,"bat_speed":73.3157760814},{"name_with_stand":"Marcus SemienR","attack_angle":13.2497953441,"attack_direction":-7.1691715534,"swing_path_tilt":32.11583428,"bat_speed":67.2781094527},{"name_with_stand":"Mark VientosR","attack_angle":15.3174389809,"attack_direction":0.7342018375,"swing_path_tilt":33.5134691038,"bat_speed":72.0774647887},{"name_with_stand":"Masyn WinnR","attack_angle":4.6215782291,"attack_direction":-2.8767266281,"swing_path_tilt":30.1305860922,"bat_speed":68.887890625},{"name_with_stand":"Matt ChapmanR","attack_angle":5.8349304634,"attack_direction":-1.0822869361,"swing_path_tilt":26.7346796623,"bat_speed":75.9583969466},{"name_with_stand":"Matt OlsonL","attack_angle":9.1806400132,"attack_direction":3.08909973,"swing_path_tilt":35.0343879058,"bat_speed":73.1076315789},{"name_with_stand":"Matt VierlingR","attack_angle":6.6221049846,"attack_direction":0.6220883646,"swing_path_tilt":30.2762814954,"bat_speed":71.2064220183},{"name_with_stand":"Michael BuschL","attack_angle":14.1996882454,"attack_direction":-2.02932693,"swing_path_tilt":38.1168536572,"bat_speed":68.6426666667},{"name_with_stand":"Mookie BettsR","attack_angle":8.3475545239,"attack_direction":-3.0558983584,"swing_path_tilt":33.9070720127,"bat_speed":67.4439655172},{"name_with_stand":"Nate LoweL","attack_angle":6.8065786319,"attack_direction":-7.7850025735,"swing_path_tilt":29.9969430905,"bat_speed":72.527016129},{"name_with_stand":"Nick CastellanosR","attack_angle":13.3113147982,"attack_direction":-4.2862252775,"swing_path_tilt":38.8211560683,"bat_speed":72.2426406926},{"name_with_stand":"Nico HoernerR","attack_angle":6.1701066388,"attack_direction":-5.0977292803,"swing_path_tilt":32.0269185228,"bat_speed":67.8334615385},{"name_with_stand":"Nolan ArenadoR","attack_angle":12.2146879849,"attack_direction":-7.8516355363,"swing_path_tilt":33.4512417967,"bat_speed":69.5132653061},{"name_with_stand":"Nolan SchanuelL","attack_angle":8.9549452189,"attack_direction":-1.2774810813,"swing_path_tilt":39.1522329799,"bat_speed":64.0697318008},{"name_with_stand":"Oneil CruzL","attack_angle":9.1081822008,"attack_direction":7.5657726285,"swing_path_tilt":32.3656216136,"bat_speed":78.2075539568},{"name_with_stand":"Orlando ArciaR","attack_angle":7.7618596852,"attack_direction":-1.5356659567,"swing_path_tilt":25.6911246931,"bat_speed":69.734551495},{"name_with_stand":"Paul GoldschmidtR","attack_angle":12.737106112,"attack_direction":-0.6555275958,"swing_path_tilt":32.6577566669,"bat_speed":72.5201277955},{"name_with_stand":"Pete AlonsoR","attack_angle":10.8495770493,"attack_direction":-2.7916327669,"swing_path_tilt":31.4635859636,"bat_speed":74.2438943894},{"name_with_stand":"Rafael DeversL","attack_angle":8.0489959887,"attack_direction":-8.6253770714,"swing_path_tilt":29.5007410755,"bat_speed":71.2380813953},{"name_with_stand":"Randy ArozarenaR","attack_angle":8.5619824979,"attack_direction":1.0449865601,"swing_path_tilt":25.4990813459,"bat_speed":70.5411111111},{"name_with_stand":"Rhys HoskinsR","attack_angle":15.8971248596,"attack_direction":-4.9268102967,"swing_path_tilt":32.9660465541,"bat_speed":69.1914772727},{"name_with_stand":"Riley GreeneL","attack_angle":11.1430678035,"attack_direction":-1.7421409659,"swing_path_tilt":44.4346774036,"bat_speed":74.2954225352},{"name_with_stand":"Ryan McMahonL","attack_angle":8.1820546914,"attack_direction":-4.4383284215,"swing_path_tilt":39.0260041376,"bat_speed":71.7306547619},{"name_with_stand":"Ryan MountcastleR","attack_angle":4.8968314733,"attack_direction":2.3436312171,"swing_path_tilt":38.2835743346,"bat_speed":74.8045901639},{"name_with_stand":"Sal FrelickL","attack_angle":5.2630419653,"attack_direction":0.6783636502,"swing_path_tilt":31.3471943596,"bat_speed":63.9642857143},{"name_with_stand":"Salvador PerezR","attack_angle":13.474386214,"attack_direction":-7.0047843871,"swing_path_tilt":35.0342474354,"bat_speed":72.8659090909},{"name_with_stand":"Seiya SuzukiR","attack_angle":7.2406942089,"attack_direction":-1.5907369673,"swing_path_tilt":29.8809783113,"bat_speed":72.8975369458},{"name_with_stand":"Shea LangeliersR","attack_angle":11.717093482,"attack_direction":-5.6639637099,"swing_path_tilt":29.7504397745,"bat_speed":73.9542319749},{"name_with_stand":"Shohei OhtaniL","attack_angle":10.9635238517,"attack_direction":-0.5670402342,"swing_path_tilt":35.459698348,"bat_speed":75.9670912951},{"name_with_stand":"Spencer SteerR","attack_angle":9.2992454962,"attack_direction":-5.2918662845,"swing_path_tilt":29.1184549847,"bat_speed":71.5484536082},{"name_with_stand":"Steven KwanL","attack_angle":4.2879365222,"attack_direction":3.704581733,"swing_path_tilt":34.5973821442,"bat_speed":63.1185185185},{"name_with_stand":"Taylor WardR","attack_angle":8.8542099865,"attack_direction":0.7179700291,"swing_path_tilt":31.5929906752,"bat_speed":68.7077170418},{"name_with_stand":"Teoscar HernandezR","attack_angle":8.9888572019,"attack_direction":2.7568140197,"swing_path_tilt":33.354527933,"bat_speed":72.5913513514},{"name_with_stand":"Trea TurnerR","attack_angle":11.4923827783,"attack_direction":-5.249402844,"swing_path_tilt":29.5652077758,"bat_speed":71.3750798722},{"name_with_stand":"Ty FranceR","attack_angle":14.7690642406,"attack_direction":4.9949797339,"swing_path_tilt":35.0997469302,"bat_speed":70.8015479876},{"name_with_stand":"Tyler StephensonR","attack_angle":10.7676079535,"attack_direction":1.7966460248,"swing_path_tilt":36.528138958,"bat_speed":69.6507518797},{"name_with_stand":"Vinnie PasquantinoL","attack_angle":9.3439053764,"attack_direction":10.8959389092,"swing_path_tilt":30.3058053467,"bat_speed":71.6532818533},{"name_with_stand":"Vladimir Guerrero Jr.R","attack_angle":4.0486418021,"attack_direction":-0.4374476301,"swing_path_tilt":28.7783349889,"bat_speed":75.5341317365},{"name_with_stand":"Will SmithR","attack_angle":14.1317907415,"attack_direction":-1.2465539335,"swing_path_tilt":35.0822229853,"bat_speed":67.2681992337},{"name_with_stand":"Willi CastroL","attack_angle":11.3480894104,"attack_direction":8.5887237315,"swing_path_tilt":39.6494378017,"bat_speed":70.3120833333},{"name_with_stand":"Willi CastroR","attack_angle":6.5633409286,"attack_direction":-8.5387134734,"swing_path_tilt":29.9584117682,"bat_speed":70.9967741935},{"name_with_stand":"William ContrerasR","attack_angle":10.0468672834,"attack_direction":3.7072660767,"swing_path_tilt":27.9221897018,"bat_speed":74.0779187817},{"name_with_stand":"Willy AdamesR","attack_angle":15.5202999413,"attack_direction":-1.6571975992,"swing_path_tilt":34.1860172786,"bat_speed":73.1746231156},{"name_with_stand":"Wyatt LangfordR","attack_angle":12.4298187475,"attack_direction":-5.832338168,"swing_path_tilt":30.7857070553,"bat_speed":74.22421875},{"name_with_stand":"Yainer DiazR","attack_angle":11.8316731699,"attack_direction":3.8501063013,"swing_path_tilt":31.1027129176,"bat_speed":72.5409836066},{"name_with_stand":"Yandy DiazR","attack_angle":2.2357172261,"attack_direction":8.0185835599,"swing_path_tilt":26.2542339333,"bat_speed":72.7686046512},{"name_with_stand":"Yordan AlvarezL","attack_angle":7.4245156573,"attack_direction":6.1364942836,"swing_path_tilt":35.2312154757,"bat_speed":75.6330357143},{"name_with_stand":"Zach NetoR","attack_angle":13.3884871469,"attack_direction":-5.1079374181,"swing_path_tilt":34.12209563,"bat_speed":68.2916666667},{"name_with_stand":"Zack GelofR","attack_angle":14.960313525,"attack_direction":3.0731603399,"swing_path_tilt":33.7838925284,"bat_speed":68.9441640379}]